{
  "version": 2,
  "extractor": "pdffigures2",
  "figures": [
    {
      "url": "assets/figures/arxiv/2605.26624v2/fig-003.webp",
      "caption": "Figure 1: Overall architecture of the proposed MSCGC-KAN model. CBraMod first extracts generic EEG representations, MCRBlock-GCN then performs multi-scale causal temporal modeling and learnable graph-based spatial modeling, and KANLinear finally maps the enhanced features to an expressive nonlinear discriminative space for emotion classification.",
      "page": 7,
      "index": 3,
      "width": 686,
      "height": 285
    },
    {
      "url": "assets/figures/arxiv/2605.26624v2/fig-006.webp",
      "caption": "Table 1: Description of Frequently Used Notations",
      "page": 8,
      "index": 6,
      "width": 677,
      "height": 352
    },
    {
      "url": "assets/figures/arxiv/2605.26624v2/fig-010.webp",
      "caption": "Table 2: Training and Reproducibility Settings",
      "page": 17,
      "index": 10,
      "width": 677,
      "height": 377
    },
    {
      "url": "assets/figures/arxiv/2605.26624v2/fig-009.webp",
      "caption": "Table 3: Performance comparison of different methods on the FACED dataset (mean±std).",
      "page": 19,
      "index": 9,
      "width": 706,
      "height": 369
    },
    {
      "url": "assets/figures/arxiv/2605.26624v2/fig-017.webp",
      "caption": "Table 4: Performance comparison of different methods on the SEED-VII dataset (mean±std).",
      "page": 20,
      "index": 17,
      "width": 706,
      "height": 225
    },
    {
      "url": "assets/figures/arxiv/2605.26624v2/fig-004.webp",
      "caption": "Figure 2: Confusion matrix on FACED. Major confusions are concentrated among emotionally similar classes, reflecting the local similarity structure of affective space.",
      "page": 23,
      "index": 4,
      "width": 586,
      "height": 274
    },
    {
      "url": "assets/figures/arxiv/2605.26624v2/fig-005.webp",
      "caption": "Figure 3: Confusion matrix on SEED-VII. The diagonal-dominant structure indicates that the model learns stable decision boundaries for most emotion categories.",
      "page": 23,
      "index": 5,
      "width": 586,
      "height": 271
    },
    {
      "url": "assets/figures/arxiv/2605.26624v2/fig-013.webp",
      "caption": "Figure 4: t-SNE visualization of stage-wise feature spaces on FACED. The three-stage comparison shows that MCRBlock-GCN and KANLinear progressively improve inter-class separability and intra-class compactness.",
      "page": 24,
      "index": 13,
      "width": 698,
      "height": 208
    },
    {
      "url": "assets/figures/arxiv/2605.26624v2/fig-014.webp",
      "caption": "Figure 5: t-SNE visualization of stage-wise feature spaces on SEED-VII. Compared with the backbone output, the graph-enhanced and KAN-mapped representations show clearer class separation.",
      "page": 24,
      "index": 14,
      "width": 698,
      "height": 206
    },
    {
      "url": "assets/figures/arxiv/2605.26624v2/fig-001.webp",
      "caption": "Figure 7: Visualization of the learnable adjacency matrix on FACED, including the learned connectivity heat map, the brain-topology graph, and the ranking of hub channels.",
      "page": 25,
      "index": 1,
      "width": 698,
      "height": 222
    },
    {
      "url": "assets/figures/arxiv/2605.26624v2/fig-002.webp",
      "caption": "Figure 8: Scalp topography visualization on FACED. Different emotions exhibit distinguishable spatial activation distributions, especially over prefrontal and temporal regions.",
      "page": 26,
      "index": 2,
      "width": 698,
      "height": 302
    },
    {
      "url": "assets/figures/arxiv/2605.26624v2/fig-011.webp",
      "caption": "Figure 9: Grad-CAM temporal heat map on FACED. High-response regions indicate the temporal segments that contribute most strongly to emotion classification.",
      "page": 27,
      "index": 11,
      "width": 698,
      "height": 252
    },
    {
      "url": "assets/figures/arxiv/2605.26624v2/fig-012.webp",
      "caption": "Figure 10: Basis-response distributions and projection-weight importance of the KAN layer on FACED. The linear term and multiple nonlinear basis functions jointly contribute to emotion-discriminative mapping.",
      "page": 27,
      "index": 12,
      "width": 710,
      "height": 231
    },
    {
      "url": "assets/figures/arxiv/2605.26624v2/fig-007.webp",
      "caption": "Figure A.12: Supplementary scalp topography visualization on SEED-VII.",
      "page": 36,
      "index": 7,
      "width": 698,
      "height": 373
    },
    {
      "url": "assets/figures/arxiv/2605.26624v2/fig-008.webp",
      "caption": "Figure A.11: Supplementary visualization of the learnable adjacency matrix on SEED-VII, including the learned connectivity heat map, the brain-topology graph, and the ranking of hub channels.",
      "page": 36,
      "index": 8,
      "width": 698,
      "height": 223
    },
    {
      "url": "assets/figures/arxiv/2605.26624v2/fig-015.webp",
      "caption": "Figure A.14: Supplementary basis-response distributions and projection-weight importance of the KAN layer on SEED-VII.",
      "page": 37,
      "index": 15,
      "width": 710,
      "height": 229
    },
    {
      "url": "assets/figures/arxiv/2605.26624v2/fig-016.webp",
      "caption": "Figure A.13: Supplementary Grad-CAM temporal heat map on SEED-VII.",
      "page": 37,
      "index": 16,
      "width": 698,
      "height": 252
    }
  ]
}