{
  "version": 2,
  "extractor": "pdffigures2",
  "figures": [
    {
      "url": "assets/figures/arxiv/2607.00410v1/fig-003.webp",
      "caption": "Figure 1: Overall architecture of MindAU. MindAU learns AU-discriminative EEG representations, aligns them with AU-level semantics and identity-reduced visual displacement trajectories, and conditions a multimodal diffusion editor for identity-preserving facial AU editing. MTP denotes the Manifold Trajectory Projector.",
      "page": 3,
      "index": 3,
      "width": 796,
      "height": 335
    },
    {
      "url": "assets/figures/arxiv/2607.00410v1/fig-002.webp",
      "caption": "Figure 2: Visual comparison of our approach with other methods. The first, second, and third rows correspond to AU25 (Lips Part), AU9 (Nose Wrinkler), and AU12 (Lip Corner Puller).",
      "page": 7,
      "index": 2,
      "width": 614,
      "height": 306
    },
    {
      "url": "assets/figures/arxiv/2607.00410v1/fig-008.webp",
      "caption": "Table 2: Ablation studies under the Self-Referenced and Cross-Referenced Editing protocols. “Direct” and “SupCon” denote pairwise cosine EEG–text alignment and supervised contrastive global-level alignment, respectively.",
      "page": 8,
      "index": 8,
      "width": 768,
      "height": 210
    },
    {
      "url": "assets/figures/arxiv/2607.00410v1/fig-007.webp",
      "caption": "Figure 4: Qualitative results of Cross-Referenced Editing.",
      "page": 8,
      "index": 7,
      "width": 599,
      "height": 226
    },
    {
      "url": "assets/figures/arxiv/2607.00410v1/fig-001.webp",
      "caption": "Figure 5: Qualitative comparison of the masking ablation under the self-reference setting.",
      "page": 15,
      "index": 1,
      "width": 576,
      "height": 228
    },
    {
      "url": "assets/figures/arxiv/2607.00410v1/fig-011.webp",
      "caption": "Figure 6: Visualization of samples from the Self-Referenced Editing test subset.",
      "page": 16,
      "index": 11,
      "width": 706,
      "height": 566
    },
    {
      "url": "assets/figures/arxiv/2607.00410v1/fig-012.webp",
      "caption": "Figure 7: Visualization of reference faces from a subset of the Cross-Referenced Editing test dataset.",
      "page": 16,
      "index": 12,
      "width": 706,
      "height": 423
    },
    {
      "url": "assets/figures/arxiv/2607.00410v1/fig-009.webp",
      "caption": "Figure 8: Qualitative results of Self-Referenced Editing on the test dataset.",
      "page": 17,
      "index": 9,
      "width": 681,
      "height": 551
    },
    {
      "url": "assets/figures/arxiv/2607.00410v1/fig-005.webp",
      "caption": "Figure 9: Qualitative results of Cross-Referenced Editing on the test dataset.",
      "page": 18,
      "index": 5,
      "width": 662,
      "height": 252
    },
    {
      "url": "assets/figures/arxiv/2607.00410v1/fig-006.webp",
      "caption": "Figure 10: Visualization of E-token feature clustering extracted by the EEG adapter on the training set. Left: labeled by AU; Right: labeled by Subject.",
      "page": 18,
      "index": 6,
      "width": 783,
      "height": 361
    },
    {
      "url": "assets/figures/arxiv/2607.00410v1/fig-004.webp",
      "caption": "Figure 11: Representative failure cases of MindAU. Some outputs exhibit incorrect AU generation or insufficient expression change, where the generated image remains overly close to the reference image.",
      "page": 18,
      "index": 4,
      "width": 679,
      "height": 271
    },
    {
      "url": "assets/figures/arxiv/2607.00410v1/fig-010.webp",
      "caption": "Table 9: Existing assets used in this work and their licenses or terms of use.",
      "page": 20,
      "index": 10,
      "width": 850,
      "height": 275
    }
  ]
}